LICENSE
README.md
setup.py
cross_sites.egg-info/PKG-INFO
cross_sites.egg-info/SOURCES.txt
cross_sites.egg-info/dependency_links.txt
cross_sites.egg-info/top_level.txt
src/__init__.py
src/main.py
src/common/__init__.py
src/common/exceptions.py
src/common/api/__init__.py
src/common/api/api_reference.py
src/common/api/docs_import.py
src/common/auth/__init__.py
src/common/auth/authentication.py
src/common/schemas/__init__.py
src/common/schemas/main.py
src/common/schemas/schema.py
src/helpers/__init__.py
src/helpers/data_serialization.py
src/helpers/json_data_helper.py
test/__init__.py