Metadata-Version: 2.1
Name: cross-sites
Version: 0.1.0
Summary: Sites common support
Author: eronrunner
Author-email: eron.runner@gmail.com
Classifier: Programming Language :: Python :: 3
Classifier: License :: OSI Approved :: MIT License
Classifier: Operating System :: OS Independent
Requires-Python: >=3.10
License-File: LICENSE
